{"id":227102,"name":"BEATLESS","name_cn":"没有心跳的少女","type":"动画","image":"82/59/227102_rs1uW.jpg","link":"https://bgm.tv/subject/227102","eps":24,"collection":{"on_hold":516,"dropped":507,"wish":1434,"collect":2339,"doing":435},"date":"2018-01-12","summary":"这是，人类与超越人智的存在之间的诀别与共存的故事。\r\n\r\n社会上的大部分都交由名为hIE的人型机器人管理的世界。\r\n17岁的少年·远藤新人，某天与一台人型机器人·蕾西亚相遇，并与之缔结了主从契约。外表与人类一模一样的“那个物体”，是具备震惊世界性能的超高性能AI所诞生出来的，超越人智的五台人型机器人“人类未到产物”之一——。\r\n五台机体各自拥有自身的意义，为了得到对方的性能而开战。\r\n仅仅只能旁观这场战斗的大人们，与接近这一存在、试图建立新的关系的少年们。他们寻求着通向未来的选择，以及人类与物体之间关系的答案——。\r\n过度进化的机械，与人类世界的联系是什么？\r\n在过于便利的这个时代，什么是重要的，什么是必要的，新人通过与远优于人类的人型机器人·蕾西亚的相遇，寻求着通向未来的选择，以及人类与物体之间关系的答案——。","rating":{"rank":6554,"total":1678,"count":{"1":18,"2":11,"3":33,"4":99,"5":280,"6":526,"7":400,"8":210,"9":55,"10":46},"score":6.3},"updated_at":"2026-07-06T23:35:46+08:00"}