{"id":302190,"name":"戦闘員、派遣します！","name_cn":"派遣战斗员！","type":"动画","image":"99/dc/302190_1NJ2Z.jpg","link":"https://bgm.tv/subject/302190","eps":12,"collection":{"on_hold":403,"dropped":490,"wish":1378,"collect":7521,"doing":707},"date":"2021-04-04","summary":"眼见征服世界的目标即将实现，为了扩大版图，「秘密结社如月」将战斗员六号作为先遣部队派遣至新侵略地，但他的各种行动却让干部们伤透脑筋。先是将侵略地的祭祀活动关键词更改为「小鸡○庆典」，还做出一连串人渣发言。不仅如此，他更主张自己获得的评价过低，要求提高工资。然而，他却传回了号称魔王军的同业，即将消灭看似人类的种族的消息──「一个世界不需要两个邪恶组织！」操起现代武器，开始进军新世界！\r\n\r\n\r\n\r\n[简介原文]\r\n秘密結社キサラギ。 今や地球上の誰もが知る大企業は、自ら悪の組織と名乗ってさまざまな悪事に手を染め、\r\nヒーローたちを打ち倒し、ついに世界征服を成し遂げようとしていた。  しかし、世界を手に入れれば大勢の戦闘員たちは不要になってしまう。 このリストラ問題を解決すべく、キサラギの最高幹部たちは\r\n新たな侵略先として宇宙に狙いを定める。  そして地球によく似た環境の惑星へ、 「戦闘員六号」と美少女型アンドロイドの「キサラギ＝アリス」を派遣するが、 現地の人々は“魔王軍”の侵略を受けていて――。","rating":{"rank":6165,"total":4395,"count":{"1":11,"2":16,"3":31,"4":144,"5":548,"6":1691,"7":1445,"8":405,"9":45,"10":59},"score":6.4},"updated_at":"2026-07-06T23:14:24+08:00"}